MANIFEST.in
README.md
setup.py
humilis_vpc/__init__.py
humilis_vpc/meta.yaml.j2
humilis_vpc/outputs.yaml.j2
humilis_vpc/plugin.py
humilis_vpc/resources.yaml.j2
humilis_vpc.egg-info/PKG-INFO
humilis_vpc.egg-info/SOURCES.txt
humilis_vpc.egg-info/dependency_links.txt
humilis_vpc.egg-info/entry_points.txt
humilis_vpc.egg-info/not-zip-safe
humilis_vpc.egg-info/requires.txt
humilis_vpc.egg-info/top_level.txt