Metadata-Version: 1.1
Name: humilis-vpc
Version: 0.2.8
Summary: Humilis plug-in to deploy a VPC
Home-page: https://github.com/humilis/humilis-vpc
Author: German Gomez-Herrero
Author-email: german@findhotel.net
License: MIT
Platform: UNKNOWN
Classifier: Programming Language :: Python :: 3
